vaex_arrow/__init__.py
vaex_arrow/_version.py
vaex_arrow/convert.py
vaex_arrow/dataset.py
vaex_arrow/export.py
vaex_arrow/opener.py
vaex_arrow-0.5.1.dist-info/LICENSE.txt
vaex_arrow-0.5.1.dist-info/METADATA
vaex_arrow-0.5.1.dist-info/WHEEL
vaex_arrow-0.5.1.dist-info/entry_points.txt
vaex_arrow-0.5.1.dist-info/top_level.txt
vaex_arrow-0.5.1.dist-info/RECORD
