Metadata-Version: 2.1
Name: vaex-arrow
Version: 0.5.1
Summary: Arrow support for vaex
Home-page: https://www.github.com/maartenbreddels/vaex
Author: Maarten A. Breddels
Author-email: maartenbreddels@gmail.com
License: MIT
Platform: UNKNOWN
Requires-Dist: vaex-core (<3,>=2.0.0)
Requires-Dist: matplotlib (>=1.3.1)
Requires-Dist: pillow
Requires-Dist: pyarrow (>=0.15)
